{
  "_format": "hh-sol-cache-2",
  "files": {
    "/home/mohsin/Documents/GitHub/lrub/contracts/landregistry.sol": {
      "lastModificationDate": 1685340159496,
      "contentHash": "cae0e5486a905ae7a33b10355a163c4e",
      "sourceName": "contracts/landregistry.sol",
      "solcConfig": {
        "version": "0.8.0",
        "settings": {
          "optimizer": {
            "enabled": true,
            "runs": 200
          },
          "outputSelection": {
            "*": {
              "*": [
                "abi",
                "evm.bytecode",
                "evm.deployedBytecode",
                "evm.methodIdentifiers",
                "metadata"
              ],
              "": [
                "ast"
              ]
            }
          }
        }
      },
      "imports": [],
      "versionPragmas": [
        "^0.8.0"
      ],
      "artifacts": [
        "landregistry"
      ]
    }
  }
}
